inv/__init__.py
inv-0.1.0.dist-info/LICENSE
inv-0.1.0.dist-info/WHEEL
inv-0.1.0.dist-info/METADATA
inv-0.1.0.dist-info/RECORD
